MAnorm2_utils/__init__.py
MAnorm2_utils/genomic_bin.py
MAnorm2_utils/htseq_read.py
MAnorm2_utils/parse_sam.py
MAnorm2_utils/scripts/__init__.py
MAnorm2_utils/scripts/profile_bins.py
MAnorm2_utils/scripts/sam2bed.py
MAnorm2_utils-1.0.0.dist-info/LICENSE.txt
MAnorm2_utils-1.0.0.dist-info/METADATA
MAnorm2_utils-1.0.0.dist-info/RECORD
MAnorm2_utils-1.0.0.dist-info/WHEEL
MAnorm2_utils-1.0.0.dist-info/entry_points.txt
MAnorm2_utils-1.0.0.dist-info/top_level.txt
