Metadata-Version: 2.1
Name: MAnorm2-utils
Version: 1.0.0
Summary: To pre-process a set of ChIP-seq samples
Home-page: https://github.com/tushiqi/MAnorm2_utils
Author: Shiqi Tu
Author-email: tushiqi@picb.ac.cn
License: UNKNOWN
Keywords: ChIP-seq MAnorm2
Platform: UNKNOWN
Classifier: Development Status :: 4 - Beta
Classifier: Operating System :: OS Independent
Classifier: Intended Audience :: Science/Research
Classifier: Topic :: Scientific/Engineering :: Bio-Informatics
Classifier: License :: OSI Approved :: GNU General Public License v3 (GPLv3)
Classifier: Programming Language :: Python :: 2
Classifier: Programming Language :: Python :: 3
